tracvatar
