Metadata-Version: 1.1
Name: tracvatar
Version: 1.9
Summary: Add gravatar icons to various points around trac
Home-page: http://bitbucket.org/zzzeek/tracvatar
Author: Mike Bayer
Author-email: mike_mp@zzzcomputing.com
License: BSD
Keywords: trac plugin gravatar
Platform: UNKNOWN
Classifier: Framework :: Trac
Classifier: Development Status :: 4 - Beta
Classifier: Environment :: Web Environment
Classifier: License :: OSI Approved :: BSD License
Classifier: Natural Language :: English
Classifier: Operating System :: OS Independent
Classifier: Programming Language :: Python
